fps_auth_base/__init__.py
fps_auth_base/py.typed
fps_auth_base-0.0.50.dist-info/METADATA
fps_auth_base-0.0.50.dist-info/WHEEL
fps_auth_base-0.0.50.dist-info/licenses/COPYING.md
fps_auth_base-0.0.50.dist-info/RECORD
