Metadata-Version: 2.1
Name: fps_auth_base
Version: 0.0.50
Summary: An FPS plugin for the authentication API
Project-URL: Homepage, https://jupyter.org
Author-email: Jupyter Development Team <jupyter@googlegroups.com>
License: BSD 3-Clause License
License-File: COPYING.md
Keywords: fastapi,jupyter,pluggy,plugins,server
Requires-Python: >=3.8
Requires-Dist: fps>=0.0.17
